replayed/__init__.py
replayed/base_types.py
replayed/constants.py
replayed/io_utils.py
replayed/utils.py
replayed/models/__init__.py
replayed/models/bsor.py
replayed/models/common.py
replayed/models/controller_offsets.py
replayed/models/cut.py
replayed/models/frame.py
replayed/models/height.py
replayed/models/info.py
replayed/models/note.py
replayed/models/pause.py
replayed/models/user_data.py
replayed/models/wall.py
replayed-0.1.0.dist-info/METADATA
replayed-0.1.0.dist-info/WHEEL
replayed-0.1.0.dist-info/top_level.txt
replayed-0.1.0.dist-info/RECORD
