Metadata-Version: 2.4
Name: replayed
Version: 0.1.0
Summary: A Python library for parsing and analyzing Beat Saber BSOR replay files.
Home-page: https://github.com/CodeSoftGit/replayed
Author: CodeSoftGit
Author-email: hello@mail.codesoft.is-a.dev
Project-URL: Bug Reports, https://github.com/CodeSoftGit/replayed/issues
Project-URL: Source, https://github.com/CodeSoftGit/replayed
Keywords: beatsaber bsor replay parser pydantic games
Classifier: Development Status :: 4 - Beta
Classifier: Intended Audience :: Developers
Classifier: Topic :: Software Development :: Libraries :: Python Modules
Classifier: Topic :: Games/Entertainment
Classifier: License :: OSI Approved :: MIT License
Classifier: Programming Language :: Python :: 3
Classifier: Programming Language :: Python :: 3.8
Classifier: Programming Language :: Python :: 3.9
Classifier: Programming Language :: Python :: 3.10
Classifier: Programming Language :: Python :: 3.11
Classifier: Programming Language :: Python :: 3.12
Classifier: Operating System :: OS Independent
Classifier: Typing :: Typed
Requires-Python: >=3.8
Requires-Dist: pydantic<3.0.0,>=2.0.0
Dynamic: author
Dynamic: author-email
Dynamic: classifier
Dynamic: description
Dynamic: description-content-type
Dynamic: home-page
Dynamic: keywords
Dynamic: project-url
Dynamic: requires-dist
Dynamic: requires-python
Dynamic: summary
